{
  "time": "2026-07-14T13:00:45.856446",
  "signals": [
    {
      "symbol": "SXTUSDT",
      "funding_rate": -0.6608,
      "p5": -0.0115,
      "price_5m_close": 0.00881,
      "score": 0.2,
      "trend": "UP",
      "time": "13:00:45"
    },
    {
      "symbol": "SKLUSDT",
      "funding_rate": -0.0274,
      "p5": -0.0271,
      "price_5m_close": 0.004704,
      "score": 0.2,
      "trend": "UP",
      "time": "13:00:45"
    },
    {
      "symbol": "EVAAUSDT",
      "funding_rate": -0.0055,
      "p5": 0.005,
      "price_5m_close": 1.1987,
      "score": 0.3,
      "trend": "UP",
      "time": "13:00:45"
    }
  ]
}